nbdotrun/__init__.py
nbdotrun/_version.py
nbdotrun-0.1.1.data/data/share/jupyter/labextensions/nbdotrun/package.json
nbdotrun-0.1.1.data/data/share/jupyter/labextensions/nbdotrun/schemas/nbdotrun/package.json.orig
nbdotrun-0.1.1.data/data/share/jupyter/labextensions/nbdotrun/schemas/nbdotrun/plugin.json
nbdotrun-0.1.1.data/data/share/jupyter/labextensions/nbdotrun/static/509.56f0ab0a39d5ba955584.js
nbdotrun-0.1.1.data/data/share/jupyter/labextensions/nbdotrun/static/728.212da25a3204f9facf54.js
nbdotrun-0.1.1.data/data/share/jupyter/labextensions/nbdotrun/static/remoteEntry.828f30e038f9bde1f00c.js
nbdotrun-0.1.1.data/data/share/jupyter/labextensions/nbdotrun/static/style.js
nbdotrun-0.1.1.data/data/share/jupyter/labextensions/nbdotrun/static/third-party-licenses.json
nbdotrun-0.1.1.data/data/share/jupyter/labextensions/nbdotrun/install.json
nbdotrun-0.1.1.dist-info/METADATA
nbdotrun-0.1.1.dist-info/WHEEL
nbdotrun-0.1.1.dist-info/licenses/LICENSE
nbdotrun-0.1.1.dist-info/RECORD
