Metadata-Version: 2.4
Name: nbdotrun
Version: 0.1.1
Summary: A JupyterLab extension that will listen for code cell changes and run if ending in dot (`.`).
Project-URL: Homepage, https://github.com/gnodar01/nbdotrun
Project-URL: Bug Tracker, https://github.com/gnodar01/nbdotrun/issues
Project-URL: Repository, https://github.com/gnodar01/nbdotrun.git
Author-email: Nodar Gogoberidze <gnodar01@gmail.com>
License: BSD 3-Clause License
License-File: LICENSE
Keywords: jupyter,jupyterlab,jupyterlab-extension
Classifier: Framework :: Jupyter
Classifier: Framework :: Jupyter :: JupyterLab
Classifier: Framework :: Jupyter :: JupyterLab :: 4
Classifier: Framework :: Jupyter :: JupyterLab :: Extensions
Classifier: Framework :: Jupyter :: JupyterLab :: Extensions :: Prebuilt
Classifier: License :: OSI Approved :: BSD License
Classifier: Programming Language :: Python
Classifier: Programming Language :: Python :: 3
Classifier: Programming Language :: Python :: 3.9
Classifier: Programming Language :: Python :: 3.10
Classifier: Programming Language :: Python :: 3.11
Classifier: Programming Language :: Python :: 3.12
Classifier: Programming Language :: Python :: 3.13
Requires-Python: >=3.9
